instaviz/__init__.py
instaviz/__main__.py
instaviz/web.py
instaviz/static/bootstrap.min.css
instaviz/static/jquery.json2html.js
instaviz/static/jquery.min.js
instaviz/static/json2html.css
instaviz/static/json2html.js
instaviz/static/node.js
instaviz/static/vis-network.min.css
instaviz/static/vis.js
instaviz/templates/home.html
instaviz-0.6.0.dist-info/LICENSE
instaviz-0.6.0.dist-info/METADATA
instaviz-0.6.0.dist-info/WHEEL
instaviz-0.6.0.dist-info/top_level.txt
instaviz-0.6.0.dist-info/RECORD
