Metadata-Version: 2.1
Name: instaviz
Version: 0.6.0
Summary: Read the latest Real Python tutorials
Home-page: https://github.com/tonybaloney/instaviz
Author: Anthony Shaw
Author-email: anthonyshaw@apache.org
License: ASF
Platform: UNKNOWN
Classifier: License :: OSI Approved :: Apache Software License
Classifier: Programming Language :: Python :: 3
Classifier: Programming Language :: Python :: 3.7
